rdopkg/__init__.py
rdopkg/action.py
rdopkg/cli.py
rdopkg/conf.py
rdopkg/const.py
rdopkg/core.py
rdopkg/exception.py
rdopkg/guess.py
rdopkg/helpers.py
rdopkg/shell.py
rdopkg/actionmods/__init__.py
rdopkg/actionmods/cbsbuild.py
rdopkg/actionmods/doctor.py
rdopkg/actionmods/kojibuild.py
rdopkg/actionmods/query.py
rdopkg/actionmods/rdoinfo.py
rdopkg/actionmods/reqs.py
rdopkg/actionmods/rpmfactory.py
rdopkg/actions/__init__.py
rdopkg/actions/build/__init__.py
rdopkg/actions/build/actions.py
rdopkg/actions/distgit/__init__.py
rdopkg/actions/distgit/actions.py
rdopkg/actions/info/__init__.py
rdopkg/actions/info/actions.py
rdopkg/actions/lint/__init__.py
rdopkg/actions/lint/actions.py
rdopkg/actions/release/__init__.py
rdopkg/actions/release/actions.py
rdopkg/actions/reqs/__init__.py
rdopkg/actions/reqs/actions.py
rdopkg/actions/review/__init__.py
rdopkg/actions/review/actions.py
rdopkg/actions/util/__init__.py
rdopkg/actions/util/actions.py
rdopkg/utils/__init__.py
rdopkg/utils/cmd.py
rdopkg/utils/distgitmagic.py
rdopkg/utils/git.py
rdopkg/utils/issues.py
rdopkg/utils/lint.py
rdopkg/utils/log.py
rdopkg/utils/specfile.py
rdopkg/utils/terminal.py
rdopkg/utils/testing.py
rdopkg-1.8.0.dist-info/AUTHORS
rdopkg-1.8.0.dist-info/LICENSE
rdopkg-1.8.0.dist-info/METADATA
rdopkg-1.8.0.dist-info/WHEEL
rdopkg-1.8.0.dist-info/entry_points.txt
rdopkg-1.8.0.dist-info/pbr.json
rdopkg-1.8.0.dist-info/top_level.txt
rdopkg-1.8.0.dist-info/RECORD
