Metadata-Version: 2.1
Name: rdopkg
Version: 1.8.0
Summary: RPM packaging automation tool
Home-page: https://github.com/softwarefactory-project/rdopkg
Author: Jakub Ruzicka
Author-email: jruzicka@redhat.com
License: Apache Software License
Classifier: Programming Language :: Python :: 3
Classifier: Programming Language :: Python :: 3.6
Classifier: Programming Language :: Python :: 3.9
Classifier: Programming Language :: Python :: 3.10
Classifier: Programming Language :: Python :: 3.11
Classifier: Programming Language :: Python :: 3.12
Classifier: Environment :: OpenStack
Classifier: Intended Audience :: Information Technology
Classifier: Intended Audience :: System Administrators
Classifier: License :: OSI Approved :: Apache Software License
Classifier: Operating System :: POSIX :: Linux
License-File: LICENSE
Requires-Dist: blessings
Requires-Dist: distroinfo (>=0.3.0)
Requires-Dist: munch
Requires-Dist: pbr (>=0.5.6)
Requires-Dist: PyYAML
Requires-Dist: pyOpenSSL (>=16.2.0)
Requires-Dist: pymod2pkg
Requires-Dist: requests
Requires-Dist: six
Provides-Extra: lint
Requires-Dist: rpmlint ; extra == 'lint'
